ibb_veri_merkezi/__init__.py
ibb_veri_merkezi/ispark.py
ibb_veri_merkezi-0.1.0.dist-info/licenses/LICENSE
ibb_veri_merkezi-0.1.0.dist-info/METADATA
ibb_veri_merkezi-0.1.0.dist-info/WHEEL
ibb_veri_merkezi-0.1.0.dist-info/top_level.txt
ibb_veri_merkezi-0.1.0.dist-info/RECORD
